<?xml version="1.0" ?>
<detailedout>
 <identity>547273344
 </identity>
 <geometry>
  <typenames> "C" "N" "H"
  </typenames>
  <typesandcoordinates>
   1 -7.3809465682452280E-002 -3.9997845787962061E-002 -1.4325899335857503E-002
 2 -8.3307285192829608E-002 -8.2957666987682602E-002 2.5433439977688836
 3 1.6850114053183720 0.20111856698510483 -1.3010972246087624
 3 1.6405528613343694 -0.14321415016086605 3.4598714201335592
 3 -1.8139087268281255 -0.23491767689355067 3.4544241526906614
 3 -1.7665802748825281 0.54076260939177301 -1.3054903839979712

  </typesandcoordinates>
  <periodic>No
  </periodic>
  <helical>No
  </helical>
 </geometry>
 <real>Yes
 </real>
 <nrofkpoints>1
 </nrofkpoints>
 <nrofspins>1
 </nrofspins>
 <nrofstates>12
 </nrofstates>
 <nroforbitals>12
 </nroforbitals>
 <kpointsandweights>
  0.0000000000000000 0.0000000000000000 0.0000000000000000 1.0000000000000000

 </kpointsandweights>
 <occupations>
  <spin1>
   <k1>
    2.0000000000000000 2.0000000000000000 2.0000000000000000 2.0000000000000000
2.0000000000000000 2.0000000000000000 0.0000000000000000 0.0000000000000000
0.0000000000000000 0.0000000000000000 0.0000000000000000 0.0000000000000000
   </k1>
  </spin1>
 </occupations>
</detailedout>
