<?xml version="1.0" ?>
<detailedout>
 <identity>916572032
 </identity>
 <geometry>
  <typenames> "C" "N" "H"
  </typenames>
  <typesandcoordinates>
   1 -5.9005862513941902E-002 3.0952483371030189E-002 5.4646944959646220E-002
 2 -8.9216704023494409E-002 -0.11819576544191152 2.4382562032631907
 3 1.6710015248595844 -0.17014796114184419 -1.0561044736071032
 3 1.4969723877906171 -3.2643618055469351E-002 3.5536503384332003
 3 -1.7294366901249756 -0.13930096227549646 3.4661399813883533
 3 -1.7877941309604564 0.35009267754819900 -1.0174871293455776

  </typesandcoordinates>
  <periodic>No
  </periodic>
  <helical>No
  </helical>
 </geometry>
 <real>Yes
 </real>
 <nrofkpoints>1
 </nrofkpoints>
 <nrofspins>2
 </nrofspins>
 <nrofstates>12
 </nrofstates>
 <nroforbitals>12
 </nroforbitals>
 <kpointsandweights>
  0.0000000000000000 0.0000000000000000 0.0000000000000000 1.0000000000000000

 </kpointsandweights>
 <occupations>
  <spin1>
   <k1>
    2.0000000000000000 2.0000000000000000 2.0000000000000000 2.0000000000000000
2.0000000000000000 1.4999718223580403 0.50002817764195984 0.0000000000000000
0.0000000000000000 0.0000000000000000 0.0000000000000000 0.0000000000000000
   </k1>
  </spin1>
  <spin2>
   <k1>
    0.0000000000000000 7.9544568980440694E-322 -5.9005862513941902E-002
3.0952483371030189E-002 5.4646944959646220E-002 -8.9216704023494409E-002
-0.11819576544191152 2.4382562032631907 1.6710015248595844 -0.17014796114184419
-1.0561044736071032 1.4969723877906171
   </k1>
  </spin2>
 </occupations>
</detailedout>
