<?xml version="1.0" ?>
<detailedout>
 <identity>1667918463
 </identity>
 <geometry>
  <typenames> "C" "N" "H"
  </typenames>
  <typesandcoordinates>
   1 -6.4788405141733521E-002 2.3198427413873950E-002 5.5158172531336473E-002
 2 -8.5514806400907833E-002 -9.1985360466621272E-002 2.4382589055713542
 3 1.6773583552153053 0.13873614207477011 -1.0398382603179526
 3 1.4912145249842363 -0.41778349393853098 3.5270796571981879
 3 -1.6990781854266754 -7.2585887002107313E-003 3.5010465085206266
 3 -1.8012640411152674 2.2448848703244234E-002 -1.0482303633578927

  </typesandcoordinates>
  <periodic>No
  </periodic>
  <helical>No
  </helical>
 </geometry>
 <real>Yes
 </real>
 <nrofkpoints>1
 </nrofkpoints>
 <nrofspins>2
 </nrofspins>
 <nrofstates>12
 </nrofstates>
 <nroforbitals>12
 </nroforbitals>
 <kpointsandweights>
  0.0000000000000000 0.0000000000000000 0.0000000000000000 1.0000000000000000

 </kpointsandweights>
 <occupations>
  <spin1>
   <k1>
    2.0000000000000000 2.0000000000000000 2.0000000000000000 2.0000000000000000
2.0000000000000000 1.4999736129043177 0.50002638709568237 0.0000000000000000
0.0000000000000000 0.0000000000000000 0.0000000000000000 0.0000000000000000
   </k1>
  </spin1>
  <spin2>
   <k1>
    0.0000000000000000 7.9544568980440694E-322 -6.4788405141733521E-002
2.3198427413873950E-002 5.5158172531336473E-002 -8.5514806400907833E-002
-9.1985360466621272E-002 2.4382589055713542 1.6773583552153053 0.13873614207477011
-1.0398382603179526 1.4912145249842363
   </k1>
  </spin2>
 </occupations>
</detailedout>
