<?xml version="1.0" ?>
<detailedout>
 <identity>1118210687
 </identity>
 <geometry>
  <typenames> "C" "N" "H"
  </typenames>
  <typesandcoordinates>
   1 -6.8202818749677582E-002 2.8871158064469247E-002 5.8500436401036589E-002
 2 -8.2331298411508241E-002 -0.10543263170408901 2.4272297844006516
 3 -3.3361506061270599E-002 -1.6650721316252204 -1.1005129020578888
 3 -0.37408754887721940 1.4183198378583355 3.5965091726760914
 3 0.16037749196583470 -1.7500970076663291 3.4477569726358359
 3 -8.8235350420365483E-002 1.8522758146769835 -0.89029681621856727

  </typesandcoordinates>
  <periodic>No
  </periodic>
  <helical>No
  </helical>
 </geometry>
 <real>Yes
 </real>
 <nrofkpoints>1
 </nrofkpoints>
 <nrofspins>2
 </nrofspins>
 <nrofstates>12
 </nrofstates>
 <nroforbitals>12
 </nroforbitals>
 <kpointsandweights>
  0.0000000000000000 0.0000000000000000 0.0000000000000000 1.0000000000000000

 </kpointsandweights>
 <occupations>
  <spin1>
   <k1>
    2.0000000000000000 2.0000000000000000 2.0000000000000000 2.0000000000000000
2.0000000000000000 1.4999782914899935 0.50002170851000660 0.0000000000000000
0.0000000000000000 0.0000000000000000 0.0000000000000000 0.0000000000000000
   </k1>
  </spin1>
  <spin2>
   <k1>
    0.0000000000000000 7.9544568980440694E-322 -6.8202818749677582E-002
2.8871158064469247E-002 5.8500436401036589E-002 -8.2331298411508241E-002
-0.10543263170408901 2.4272297844006516 -3.3361506061270599E-002
-1.6650721316252204 -1.1005129020578888 -0.37408754887721940
   </k1>
  </spin2>
 </occupations>
</detailedout>
