<?xml version="1.0" ?>
<detailedout>
 <identity>117140352
 </identity>
 <geometry>
  <typenames> "C" "N" "H"
  </typenames>
  <typesandcoordinates>
   1 -9.2586161050170174E-002 0.17812749920395765 -0.32739841013081800
 2 -0.14505387399978717 -0.26853199049757331 2.7392294410601163
 3 -1.1225958620152243 1.9133788950930504 -1.3573125476526298
 3 -1.1989517523645468 -1.6815645829097237 3.5293891669178694
 3 1.3828020221632771 0.91159091006197057 3.6892018575802377
 3 1.7658366488087625 -0.79974105235956583 -0.54469140641380831

  </typesandcoordinates>
  <periodic>No
  </periodic>
  <helical>No
  </helical>
 </geometry>
 <real>Yes
 </real>
 <nrofkpoints>1
 </nrofkpoints>
 <nrofspins>2
 </nrofspins>
 <nrofstates>12
 </nrofstates>
 <nroforbitals>12
 </nroforbitals>
 <kpointsandweights>
  0.0000000000000000 0.0000000000000000 0.0000000000000000 1.0000000000000000

 </kpointsandweights>
 <occupations>
  <spin1>
   <k1>
    2.0000000000000000 2.0000000000000000 2.0000000000000000 2.0000000000000000
2.0000000000000000 1.4999999999070299 0.50000000009297019 0.0000000000000000
0.0000000000000000 0.0000000000000000 0.0000000000000000 0.0000000000000000
   </k1>
  </spin1>
  <spin2>
   <k1>
    0.0000000000000000 7.9544568980440694E-322 -9.2586161050170174E-002
0.17812749920395765 -0.32739841013081800 -0.14505387399978717 -0.26853199049757331
2.7392294410601163 -1.1225958620152243 1.9133788950930504 -1.3573125476526298
-1.1989517523645468
   </k1>
  </spin2>
 </occupations>
</detailedout>
