<?xml version="1.0" ?>
<detailedout>
 <identity>218521728
 </identity>
 <geometry>
  <typenames> "C" "N" "H"
  </typenames>
  <typesandcoordinates>
   1 -6.9775240847514214E-002 2.8223057639426219E-004 -1.5565389509026304E-002
 2 -6.7343333575552111E-002 -5.5436699244793115E-002 2.5425855940378876
 3 1.5752514711757761 0.70745422390598656 -1.2625285974832225
 3 1.4207191851515142 -1.0401982153242570 3.4204528509501362
 3 -1.7467199161466598 0.27314968712874504 3.4979991552887038
 3 -1.7740987575979483 -0.43910311798004004 -1.3228742379285472

  </typesandcoordinates>
  <periodic>No
  </periodic>
  <helical>No
  </helical>
 </geometry>
 <real>Yes
 </real>
 <nrofkpoints>1
 </nrofkpoints>
 <nrofspins>1
 </nrofspins>
 <nrofstates>12
 </nrofstates>
 <nroforbitals>12
 </nroforbitals>
 <kpointsandweights>
  0.0000000000000000 0.0000000000000000 0.0000000000000000 1.0000000000000000

 </kpointsandweights>
 <occupations>
  <spin1>
   <k1>
    2.0000000000000000 2.0000000000000000 2.0000000000000000 2.0000000000000000
2.0000000000000000 2.0000000000000000 0.0000000000000000 0.0000000000000000
0.0000000000000000 0.0000000000000000 0.0000000000000000 0.0000000000000000
   </k1>
  </spin1>
 </occupations>
</detailedout>
