<?xml version="1.0" ?>
<detailedout>
 <identity>1839454079
 </identity>
 <geometry>
  <typenames> "C" "N" "H"
  </typenames>
  <typesandcoordinates>
   1 -0.42400726868739591 -0.14296204181672972 -6.2576575358401325E-003
 2 0.29689553036699051 -4.0562968344846591E-004 2.5036918773505321
 3 -2.0529577226779074 1.0033148269380718 -1.4829471438595427
 3 -2.1989024513032307 1.0017938998734242 2.5724805489511890
 3 1.6037138815089158 -0.67605988480430690 4.3366891043344911
 3 1.2834209355814541 -0.88510477516768682 -0.66296808992255074

  </typesandcoordinates>
  <periodic>No
  </periodic>
  <helical>No
  </helical>
 </geometry>
 <real>Yes
 </real>
 <nrofkpoints>1
 </nrofkpoints>
 <nrofspins>2
 </nrofspins>
 <nrofstates>12
 </nrofstates>
 <nroforbitals>12
 </nroforbitals>
 <kpointsandweights>
  0.0000000000000000 0.0000000000000000 0.0000000000000000 1.0000000000000000

 </kpointsandweights>
 <occupations>
  <spin1>
   <k1>
    2.0000000000000000 2.0000000000000000 2.0000000000000000 2.0000000000000000
2.0000000000000000 1.4994222668164254 0.50057773318357457 0.0000000000000000
0.0000000000000000 0.0000000000000000 0.0000000000000000 0.0000000000000000
   </k1>
  </spin1>
  <spin2>
   <k1>
    0.0000000000000000 7.9544568980440694E-322 -0.42400726868739591
-0.14296204181672972 -6.2576575358401325E-003 0.29689553036699051
-4.0562968344846591E-004 2.5036918773505321 -2.0529577226779074 1.0033148269380718
-1.4829471438595427 -2.1989024513032307
   </k1>
  </spin2>
 </occupations>
</detailedout>
