<?xml version="1.0" ?>
<detailedout>
 <identity>2098503935
 </identity>
 <geometry>
  <typenames> "C" "N" "H"
  </typenames>
  <typesandcoordinates>
   1 -0.10861640425512700 0.15784280249735377 -3.5666518233099624E-002
 2 -6.3792519545752421E-002 -9.2397037273233187E-002 2.5336750068784610
 3 1.7125084680275058 8.0401888177169159E-002 -1.2225454726607115
 3 1.2968889371130166 -1.2585511778115011 3.4224550912240752
 3 -1.6379801127844784 0.49064407151033812 3.5694274339447274
 3 -1.4827778244109660 -1.1750675244921576 -1.0729331638367545

  </typesandcoordinates>
  <periodic>No
  </periodic>
  <helical>No
  </helical>
 </geometry>
 <real>Yes
 </real>
 <nrofkpoints>1
 </nrofkpoints>
 <nrofspins>1
 </nrofspins>
 <nrofstates>12
 </nrofstates>
 <nroforbitals>12
 </nroforbitals>
 <kpointsandweights>
  0.0000000000000000 0.0000000000000000 0.0000000000000000 1.0000000000000000

 </kpointsandweights>
 <occupations>
  <spin1>
   <k1>
    2.0000000000000000 2.0000000000000000 2.0000000000000000 2.0000000000000000
2.0000000000000000 2.0000000000000000 0.0000000000000000 0.0000000000000000
0.0000000000000000 0.0000000000000000 0.0000000000000000 0.0000000000000000
   </k1>
  </spin1>
 </occupations>
</detailedout>
