<?xml version="1.0" ?>
<detailedout>
 <identity>1988703359
 </identity>
 <geometry>
  <typenames> "C" "N" "H"
  </typenames>
  <typesandcoordinates>
   1 -3.4187845441556390E-002 -0.11410896842997119 -5.7482384319209462E-002
 2 -9.6665947178692868E-002 -9.6325418555550948E-002 2.5401102041709280
 3 1.4011157157665333 1.2620758758281387 -0.95235562555335784
 3 1.4884809985472371 -0.76957709495179005 3.4898927221264571
 3 -1.5702955702844283 0.78121733460993903 3.5240999750539159
 3 -1.8607356643936142 0.15889711842090173 -1.1946798188975052

  </typesandcoordinates>
  <periodic>No
  </periodic>
  <helical>No
  </helical>
 </geometry>
 <real>Yes
 </real>
 <nrofkpoints>1
 </nrofkpoints>
 <nrofspins>1
 </nrofspins>
 <nrofstates>12
 </nrofstates>
 <nroforbitals>12
 </nroforbitals>
 <kpointsandweights>
  0.0000000000000000 0.0000000000000000 0.0000000000000000 1.0000000000000000

 </kpointsandweights>
 <occupations>
  <spin1>
   <k1>
    2.0000000000000000 2.0000000000000000 2.0000000000000000 2.0000000000000000
2.0000000000000000 2.0000000000000000 0.0000000000000000 0.0000000000000000
0.0000000000000000 0.0000000000000000 0.0000000000000000 0.0000000000000000
   </k1>
  </spin1>
 </occupations>
</detailedout>
