<?xml version="1.0" ?>
<detailedout>
 <identity>720117760
 </identity>
 <geometry>
  <typenames> "C" "H" "N"
  </typenames>
  <typesandcoordinates>
   1 -11.313053709911101 -1.5812027285398282 -0.50496125920938828
 1 -8.8244919614826465 -1.3239595831528277 0.29880636459486187
 2 -11.751174283760639 1.1649026883995914E-002 -1.6082752832028877
 2 -12.618654000372567 -3.0090906270235367 -0.20200685158329626
 2 -8.3063819699474646 -2.5943543162415890 1.9172978088481654
 1 -7.1794334453709672 0.93470286361460719 -0.33467874957715732
 1 -4.8511593324375895 1.0476828341499618 0.65643133875545734
 2 -8.0653265953238300 2.6919448496547140 -1.4654419884177599
 2 -4.5426628498157529 -0.55426919912802219 2.1932422495359396
 1 -3.2856413485002265 3.1878427751530189 0.97446908568814916
 2 -3.6097783183418755 4.9383615318654783 2.1396393025959437
 3 -1.3375966962631078 3.2850142996226963 -0.34218449553941427
 2 -0.11421566235928636 4.8597515007679402 -0.26130970343360321
 2 -1.2146957587740133 1.5951742475610473 -1.4719164920107894

  </typesandcoordinates>
  <periodic>No
  </periodic>
  <helical>No
  </helical>
 </geometry>
 <real>Yes
 </real>
 <nrofkpoints>1
 </nrofkpoints>
 <nrofspins>2
 </nrofspins>
 <nrofstates>32
 </nrofstates>
 <nroforbitals>32
 </nroforbitals>
 <kpointsandweights>
  0.0000000000000000 0.0000000000000000 0.0000000000000000 1.0000000000000000

 </kpointsandweights>
 <occupations>
  <spin1>
   <k1>
    2.0000000000000000 2.0000000000000000 2.0000000000000000 2.0000000000000000
2.0000000000000000 2.0000000000000000 2.0000000000000000 2.0000000000000000
2.0000000000000000 2.0000000000000000 2.0000000000000000 2.0000000000000000
2.0000000000000000 2.0000000000000000 2.0000000000000000 1.4999999999978659
0.50000000000213407 0.0000000000000000 0.0000000000000000 0.0000000000000000
0.0000000000000000 0.0000000000000000 0.0000000000000000 0.0000000000000000
0.0000000000000000 0.0000000000000000 0.0000000000000000 0.0000000000000000
0.0000000000000000 0.0000000000000000 0.0000000000000000 0.0000000000000000
   </k1>
  </spin1>
  <spin2>
   <k1>
    0.0000000000000000 1.7440517298196003E-321 -11.313053709911101 -1.5812027285398282
-0.50496125920938828 -8.8244919614826465 -1.3239595831528277 0.29880636459486187
-11.751174283760639 1.1649026883995914E-002 -1.6082752832028877 -12.618654000372567
-3.0090906270235367 -0.20200685158329626 -8.3063819699474646 -2.5943543162415890
1.9172978088481654 -7.1794334453709672 0.93470286361460719 -0.33467874957715732
-4.8511593324375895 1.0476828341499618 0.65643133875545734 -8.0653265953238300
2.6919448496547140 -1.4654419884177599 -4.5426628498157529 -0.55426919912802219
2.1932422495359396 -3.2856413485002265 3.1878427751530189 0.97446908568814916
   </k1>
  </spin2>
 </occupations>
</detailedout>
