<?xml version="1.0" ?>
<detailedout>
 <identity>316958976
 </identity>
 <geometry>
  <typenames> "C" "N" "H"
  </typenames>
  <typesandcoordinates>
   1 -6.5201858290774711E-002 -4.6584542412933555E-002 -0.21941445936954859
 2 -7.1980513281666048E-002 -0.22966380400832390 2.6914256474393521
 3 1.6988199354730762 -2.9725238622267381E-002 -1.3410102028025774
 3 1.1358701288384376 1.2735658066811562 3.2765951735011196
 3 -1.7795754669717481 -6.7394375074503632E-002 3.6516722207004784
 3 -1.5700335786733719 1.3044584046356082 -0.89344863350313841

  </typesandcoordinates>
  <periodic>No
  </periodic>
  <helical>No
  </helical>
 </geometry>
 <real>Yes
 </real>
 <nrofkpoints>1
 </nrofkpoints>
 <nrofspins>1
 </nrofspins>
 <nrofstates>12
 </nrofstates>
 <nroforbitals>12
 </nroforbitals>
 <kpointsandweights>
  0.0000000000000000 0.0000000000000000 0.0000000000000000 1.0000000000000000

 </kpointsandweights>
 <occupations>
  <spin1>
   <k1>
    2.0000000000000000 2.0000000000000000 2.0000000000000000 2.0000000000000000
2.0000000000000000 2.0000000000000000 0.0000000000000000 0.0000000000000000
0.0000000000000000 0.0000000000000000 0.0000000000000000 0.0000000000000000
   </k1>
  </spin1>
 </occupations>
</detailedout>
