<?xml version="1.0" ?>
<detailedout>
 <identity>2040208511
 </identity>
 <geometry>
  <typenames> "C" "N" "H"
  </typenames>
  <typesandcoordinates>
   1 -9.6611012844204869E-002 1.8604503535638587E-002 4.5953714083426141E-002
 2 -6.0917339248649366E-002 -0.10368626032900367 2.4383319056862929
 3 0.36912376782849937 1.8799209752118424 -0.74264148873112268
 3 -0.10729044022072083 -1.7992101168355408 3.3570426418691328
 3 2.7640020480169964E-002 1.5234824655131762 3.5227189633014628
 3 -0.58386495372555214 -1.6507284688650703 -1.0883691260128230

  </typesandcoordinates>
  <periodic>No
  </periodic>
  <helical>No
  </helical>
 </geometry>
 <real>Yes
 </real>
 <nrofkpoints>1
 </nrofkpoints>
 <nrofspins>2
 </nrofspins>
 <nrofstates>12
 </nrofstates>
 <nroforbitals>12
 </nroforbitals>
 <kpointsandweights>
  0.0000000000000000 0.0000000000000000 0.0000000000000000 1.0000000000000000

 </kpointsandweights>
 <occupations>
  <spin1>
   <k1>
    2.0000000000000000 2.0000000000000000 2.0000000000000000 2.0000000000000000
2.0000000000000000 1.4999719664242013 0.50002803357579872 0.0000000000000000
0.0000000000000000 0.0000000000000000 0.0000000000000000 0.0000000000000000
   </k1>
  </spin1>
  <spin2>
   <k1>
    0.0000000000000000 7.9544568980440694E-322 -9.6611012844204869E-002
1.8604503535638587E-002 4.5953714083426141E-002 -6.0917339248649366E-002
-0.10368626032900367 2.4383319056862929 0.36912376782849937 1.8799209752118424
-0.74264148873112268 -0.10729044022072083
   </k1>
  </spin2>
 </occupations>
</detailedout>
