<?xml version="1.0" ?>
<detailedout>
 <identity>1056424320
 </identity>
 <geometry>
  <typenames> "C" "N" "H"
  </typenames>
  <typesandcoordinates>
   1 -6.5078856026178092E-002 -3.5845909921195421E-002 -0.40434616265976320
 2 -9.6725284574734241E-002 -0.27584702531306293 2.8593708305853487
 3 1.7746395593813595 0.66222459612960416 -1.1061519010995879
 3 1.5603910817413089 0.69174884349572641 3.3685601249270642
 3 -1.6476253498192248 0.78017549087791571 3.3573225858770814
 3 -1.8598894828904482 0.86059835501355808 -1.0561019602715385

  </typesandcoordinates>
  <periodic>No
  </periodic>
  <helical>No
  </helical>
 </geometry>
 <real>Yes
 </real>
 <nrofkpoints>1
 </nrofkpoints>
 <nrofspins>1
 </nrofspins>
 <nrofstates>12
 </nrofstates>
 <nroforbitals>12
 </nroforbitals>
 <kpointsandweights>
  0.0000000000000000 0.0000000000000000 0.0000000000000000 1.0000000000000000

 </kpointsandweights>
 <occupations>
  <spin1>
   <k1>
    2.0000000000000000 2.0000000000000000 2.0000000000000000 2.0000000000000000
2.0000000000000000 2.0000000000000000 0.0000000000000000 0.0000000000000000
0.0000000000000000 0.0000000000000000 0.0000000000000000 0.0000000000000000
   </k1>
  </spin1>
 </occupations>
</detailedout>
