<?xml version="1.0" ?>
<detailedout>
 <identity>967253120
 </identity>
 <geometry>
  <typenames> "C" "N" "H"
  </typenames>
  <typesandcoordinates>
   1 -0.10992405684470385 -0.10903520532871586 -6.1526889263525383E-002
 2 -7.3544733968712250E-002 -9.2210143372962738E-002 2.5478068502525510
 3 1.7179585322648669 7.5883742311075822E-002 -1.1903383057195642
 3 1.5282225219021086 0.51602069158494757 3.5262761268105844
 3 -1.7381549409732844 -0.59021384723212100 3.4879548270224294
 3 -1.4682551857024375 1.3132340842567101 -1.0156995619439415

  </typesandcoordinates>
  <periodic>No
  </periodic>
  <helical>No
  </helical>
 </geometry>
 <real>Yes
 </real>
 <nrofkpoints>1
 </nrofkpoints>
 <nrofspins>1
 </nrofspins>
 <nrofstates>12
 </nrofstates>
 <nroforbitals>12
 </nroforbitals>
 <kpointsandweights>
  0.0000000000000000 0.0000000000000000 0.0000000000000000 1.0000000000000000

 </kpointsandweights>
 <occupations>
  <spin1>
   <k1>
    2.0000000000000000 2.0000000000000000 2.0000000000000000 2.0000000000000000
2.0000000000000000 2.0000000000000000 0.0000000000000000 0.0000000000000000
0.0000000000000000 0.0000000000000000 0.0000000000000000 0.0000000000000000
   </k1>
  </spin1>
 </occupations>
</detailedout>
