<?xml version="1.0" ?>
<detailedout>
 <identity>402328704
 </identity>
 <geometry>
  <typenames> "C" "N" "H"
  </typenames>
  <typesandcoordinates>
   1 -0.12147211566912998 2.7543474379413468E-002 3.3618187542299276E-002
 2 -1.9135119695971661E-002 -0.11011894428590599 2.4561979232028550
 3 0.42547564247230141 1.8367378828865715 -0.80965491394358868
 3 -8.4328001788300619E-002 -1.8234876911724527 3.3395389604136216
 3 -0.18704602321253611 1.5449784954757191 3.4561646281206624
 3 -0.73283570057638669 -1.6219066704434228 -1.0386051196241055

  </typesandcoordinates>
  <periodic>No
  </periodic>
  <helical>No
  </helical>
 </geometry>
 <real>Yes
 </real>
 <nrofkpoints>1
 </nrofkpoints>
 <nrofspins>2
 </nrofspins>
 <nrofstates>12
 </nrofstates>
 <nroforbitals>12
 </nroforbitals>
 <kpointsandweights>
  0.0000000000000000 0.0000000000000000 0.0000000000000000 1.0000000000000000

 </kpointsandweights>
 <occupations>
  <spin1>
   <k1>
    2.0000000000000000 2.0000000000000000 2.0000000000000000 2.0000000000000000
2.0000000000000000 1.4999377716690008 0.50006222833099923 0.0000000000000000
0.0000000000000000 0.0000000000000000 0.0000000000000000 0.0000000000000000
   </k1>
  </spin1>
  <spin2>
   <k1>
    0.0000000000000000 7.9544568980440694E-322 -0.12147211566912998
2.7543474379413468E-002 3.3618187542299276E-002 -1.9135119695971661E-002
-0.11011894428590599 2.4561979232028550 0.42547564247230141 1.8367378828865715
-0.80965491394358868 -8.4328001788300619E-002
   </k1>
  </spin2>
 </occupations>
</detailedout>
