<?xml version="1.0" ?>
<detailedout>
 <identity>13524096
 </identity>
 <geometry>
  <typenames> "C" "N" "H"
  </typenames>
  <typesandcoordinates>
   1 -0.11486663516783202 9.0996920391035185E-003 3.9842567003480531E-002
 2 -3.1827955627019032E-002 -9.3401747889580944E-002 2.4501555054571140
 3 0.44661630946269198 1.8148175149532932 -0.80049199167290741
 3 -9.1025020616485347E-002 -1.7994514348442823 3.3467777825799918
 3 -0.14821899495531790 1.5607809889045325 3.4634802487512082
 3 -0.68845571250172932 -1.6523715667148797 -1.0525239908792829

  </typesandcoordinates>
  <periodic>No
  </periodic>
  <helical>No
  </helical>
 </geometry>
 <real>Yes
 </real>
 <nrofkpoints>1
 </nrofkpoints>
 <nrofspins>2
 </nrofspins>
 <nrofstates>12
 </nrofstates>
 <nroforbitals>12
 </nroforbitals>
 <kpointsandweights>
  0.0000000000000000 0.0000000000000000 0.0000000000000000 1.0000000000000000

 </kpointsandweights>
 <occupations>
  <spin1>
   <k1>
    2.0000000000000000 2.0000000000000000 2.0000000000000000 2.0000000000000000
2.0000000000000000 1.4999489389865168 0.50005106101348329 0.0000000000000000
0.0000000000000000 0.0000000000000000 0.0000000000000000 0.0000000000000000
   </k1>
  </spin1>
  <spin2>
   <k1>
    0.0000000000000000 7.9544568980440694E-322 -0.11486663516783202
9.0996920391035185E-003 3.9842567003480531E-002 -3.1827955627019032E-002
-9.3401747889580944E-002 2.4501555054571140 0.44661630946269198 1.8148175149532932
-0.80049199167290741 -9.1025020616485347E-002
   </k1>
  </spin2>
 </occupations>
</detailedout>
