<?xml version="1.0" ?>
<detailedout>
 <identity>560787072
 </identity>
 <geometry>
  <typenames> "C" "N" "H"
  </typenames>
  <typesandcoordinates>
   1 -7.3193377215655775E-002 3.7413815573919353E-002 5.4436202717399892E-002
 2 -8.2839766983255181E-002 -0.11400919089777423 2.4384709517245327
 3 0.40078181819188530 1.8103470846684115 -0.89538467667569743
 3 -7.7192056304748666E-002 -1.8017575430571848 3.3809282681387538
 3 -4.6503567654322946E-002 1.4501629112932630 3.5890057699740603
 3 -0.54582017754130630 -1.5859567122092961 -1.1287341077658462

  </typesandcoordinates>
  <periodic>No
  </periodic>
  <helical>No
  </helical>
 </geometry>
 <real>Yes
 </real>
 <nrofkpoints>1
 </nrofkpoints>
 <nrofspins>2
 </nrofspins>
 <nrofstates>12
 </nrofstates>
 <nroforbitals>12
 </nroforbitals>
 <kpointsandweights>
  0.0000000000000000 0.0000000000000000 0.0000000000000000 1.0000000000000000

 </kpointsandweights>
 <occupations>
  <spin1>
   <k1>
    2.0000000000000000 2.0000000000000000 2.0000000000000000 2.0000000000000000
2.0000000000000000 1.4999652415743521 0.50003475842564793 0.0000000000000000
0.0000000000000000 0.0000000000000000 0.0000000000000000 0.0000000000000000
   </k1>
  </spin1>
  <spin2>
   <k1>
    0.0000000000000000 7.9544568980440694E-322 -7.3193377215655775E-002
3.7413815573919353E-002 5.4436202717399892E-002 -8.2839766983255181E-002
-0.11400919089777423 2.4384709517245327 0.40078181819188530 1.8103470846684115
-0.89538467667569743 -7.7192056304748666E-002
   </k1>
  </spin2>
 </occupations>
</detailedout>
