<?xml version="1.0" ?>
<detailedout>
 <identity>1607127423
 </identity>
 <geometry>
  <typenames> "C" "N" "H"
  </typenames>
  <typesandcoordinates>
   1 -6.7653002973300541E-002 0.14378915598467085 -0.42507216707647993
 2 -7.7476063223572186E-002 3.1954453884694499E-002 2.8996183658681818
 3 1.6896843953319696 -0.70877877064590133 -1.1501946864688433
 3 1.4694531774928972 -1.1509695308159404 3.3542107173999085
 3 -1.6660032185170532 -1.0794496004494707 3.3091999765847833
 3 -1.9024579229406742 -0.48395330767517558 -1.2619095043521040

  </typesandcoordinates>
  <periodic>No
  </periodic>
  <helical>No
  </helical>
 </geometry>
 <real>Yes
 </real>
 <nrofkpoints>1
 </nrofkpoints>
 <nrofspins>1
 </nrofspins>
 <nrofstates>12
 </nrofstates>
 <nroforbitals>12
 </nroforbitals>
 <kpointsandweights>
  0.0000000000000000 0.0000000000000000 0.0000000000000000 1.0000000000000000

 </kpointsandweights>
 <occupations>
  <spin1>
   <k1>
    2.0000000000000000 2.0000000000000000 2.0000000000000000 2.0000000000000000
2.0000000000000000 2.0000000000000000 0.0000000000000000 0.0000000000000000
0.0000000000000000 0.0000000000000000 0.0000000000000000 0.0000000000000000
   </k1>
  </spin1>
 </occupations>
</detailedout>
