<?xml version="1.0" ?>
<detailedout>
 <identity>1452464895
 </identity>
 <geometry>
  <typenames> "C" "N" "H"
  </typenames>
  <typesandcoordinates>
   1 -6.0015599801419274E-002 0.13357569724241869 -0.39073677182973526
 2 -7.7926441618430195E-002 3.3663635452324599E-002 2.8723180614289787
 3 1.7520300272773064 -0.40378591559592919 -1.2907893173616012
 3 1.3459999864809002 -1.3575847815785445 3.2063779824366563
 3 -1.7481599629389963 -0.84040349588045127 3.3886609701922392
 3 -1.8439223754307699 -0.72343004300247238 -1.0827603625869411

  </typesandcoordinates>
  <periodic>No
  </periodic>
  <helical>No
  </helical>
 </geometry>
 <real>Yes
 </real>
 <nrofkpoints>1
 </nrofkpoints>
 <nrofspins>1
 </nrofspins>
 <nrofstates>12
 </nrofstates>
 <nroforbitals>12
 </nroforbitals>
 <kpointsandweights>
  0.0000000000000000 0.0000000000000000 0.0000000000000000 1.0000000000000000

 </kpointsandweights>
 <occupations>
  <spin1>
   <k1>
    2.0000000000000000 2.0000000000000000 2.0000000000000000 2.0000000000000000
2.0000000000000000 2.0000000000000000 0.0000000000000000 0.0000000000000000
0.0000000000000000 0.0000000000000000 0.0000000000000000 0.0000000000000000
   </k1>
  </spin1>
 </occupations>
</detailedout>
