<?xml version="1.0" ?>
<detailedout>
 <identity>1926967679
 </identity>
 <geometry>
  <typenames> "C" "N" "H"
  </typenames>
  <typesandcoordinates>
   1 -6.3532436557944313E-002 0.11682367319612413 -2.3185993016869100E-003
 2 -6.7326155966315929E-002 -1.1505577784202890E-002 2.5134657669305813
 3 1.5837846800552835 0.24760741367397676 -1.3271248741836974
 3 0.97545824385961089 -1.5842676373261846 3.1500541324292648
 3 -1.7118526386231696 0.13156937516034442 3.6183343362140650
 3 -1.4468416044847765 -1.2928207350048038 -0.86137699770989207

  </typesandcoordinates>
  <periodic>No
  </periodic>
  <helical>No
  </helical>
 </geometry>
 <real>Yes
 </real>
 <nrofkpoints>1
 </nrofkpoints>
 <nrofspins>1
 </nrofspins>
 <nrofstates>12
 </nrofstates>
 <nroforbitals>12
 </nroforbitals>
 <kpointsandweights>
  0.0000000000000000 0.0000000000000000 0.0000000000000000 1.0000000000000000

 </kpointsandweights>
 <occupations>
  <spin1>
   <k1>
    2.0000000000000000 2.0000000000000000 2.0000000000000000 2.0000000000000000
2.0000000000000000 2.0000000000000000 0.0000000000000000 0.0000000000000000
0.0000000000000000 0.0000000000000000 0.0000000000000000 0.0000000000000000
   </k1>
  </spin1>
 </occupations>
</detailedout>
